izipyzi/__init__.py
izipyzi/stats.py
izipyzi/time.py
izipyzi-0.1.0.dist-info/LICENSE
izipyzi-0.1.0.dist-info/METADATA
izipyzi-0.1.0.dist-info/WHEEL
izipyzi-0.1.0.dist-info/RECORD
