Metadata-Version: 2.1
Name: izipyzi
Version: 0.1.0
Summary: 
Author: Armand Sauzay
Author-email: sauzayarmand@gmail.com
Requires-Python: >=3.10,<4
Classifier: Programming Language :: Python :: 3
Classifier: Programming Language :: Python :: 3.10
Classifier: Programming Language :: Python :: 3.11
Classifier: Programming Language :: Python :: 3.12
Requires-Dist: numpy (>=1.26.4)
